.flake8
CHANGES.txt
CONTRIBUTING.md
CREDITS.txt
LICENSE.txt
README.md
VERSION.txt
nose2.cfg
requirements-dev.txt
requirements-main.txt
setup.py
Stetl.egg-info/PKG-INFO
Stetl.egg-info/SOURCES.txt
Stetl.egg-info/dependency_links.txt
Stetl.egg-info/namespace_packages.txt
Stetl.egg-info/requires.txt
Stetl.egg-info/top_level.txt
Stetl.egg-info/zip-safe
bin/stetl
docs/.DS_Store
docs/Makefile
docs/background.rst
docs/cases.rst
docs/code.rst
docs/conf.py
docs/contact.rst
docs/foss4g13-abstract.txt
docs/index.rst
docs/install.rst
docs/intro.rst
docs/links.rst
docs/make.bat
docs/py3upgrade.rst
docs/using.rst
docs/_static/default.css
examples/.DS_Store
examples/README.md
examples/basics/.DS_Store
examples/basics/README.md
examples/basics/runall-docker.log
examples/basics/runall-docker.sh
examples/basics/runall.log
examples/basics/runall.sh
examples/basics/10_jinja2_templating/.DS_Store
examples/basics/10_jinja2_templating/etl.cfg
examples/basics/10_jinja2_templating/etl.sh
examples/basics/10_jinja2_templating/gmlcities.xsd
examples/basics/10_jinja2_templating/readme.txt
examples/basics/10_jinja2_templating/input/addresses-globals.json
examples/basics/10_jinja2_templating/input/addresses.csv
examples/basics/10_jinja2_templating/input/cities-gjson.json
examples/basics/10_jinja2_templating/input/cities.json
examples/basics/10_jinja2_templating/input/globals.json
examples/basics/10_jinja2_templating/input/more-globals.json
examples/basics/10_jinja2_templating/output/cities-gjson.gml
examples/basics/10_jinja2_templating/output/cities.gml
examples/basics/10_jinja2_templating/output/cities.xml
examples/basics/10_jinja2_templating/output/inspire-addresses.gml
examples/basics/10_jinja2_templating/templates/addresses2inspire-ad.jinja2
examples/basics/10_jinja2_templating/templates/cities-gjson2gml.jinja2
examples/basics/10_jinja2_templating/templates/cities-json2gml.jinja2
examples/basics/10_jinja2_templating/templates/cities-json2xml.jinja2
examples/basics/10_jinja2_templating/templates/macros-inspire.jinja2
examples/basics/10_jinja2_templating/templates/macros.jinja2
examples/basics/11_formatconvert/.DS_Store
examples/basics/11_formatconvert/etl.cfg
