Metadata-Version: 2.1
Name: Stetl
Version: 2.1
Summary: Transformation and conversion framework (ETL) mainly for geospatial data
Home-page: http://github.com/geopython/stetl
Author: Just van den Broecke
Author-email: justb4@gmail.com
Maintainer: Just van den Broecke
Maintainer-email: justb4@gmail.com
License: GNU GPL v3
Keywords: etl xsl gdal gis vector feature data gml xml
Platform: UNKNOWN
Classifier: Development Status :: 5 - Production/Stable
Classifier: Environment :: Console
Classifier: Intended Audience :: Developers
Classifier: Intended Audience :: Science/Research
Classifier: License :: OSI Approved :: GNU General Public License v3 (GPLv3)
Classifier: Operating System :: OS Independent
Classifier: Programming Language :: Python :: 3.6
Classifier: Programming Language :: Python :: 3.7
Classifier: Programming Language :: Python :: 3.8
Classifier: Topic :: Scientific/Engineering :: GIS
